pyidaungsu/__init__.py
pyidaungsu/tokenize.py
pyidaungsu/model/pdsdetect.ftz
pyidaungsu/model/tokenizer.crfsuite
pyidaungsu/model/lib/fasttext_pybind.cpython-38-x86_64-linux-gnu.so
pyidaungsu-0.1.3.dist-info/LICENSE
pyidaungsu-0.1.3.dist-info/METADATA
pyidaungsu-0.1.3.dist-info/WHEEL
pyidaungsu-0.1.3.dist-info/top_level.txt
pyidaungsu-0.1.3.dist-info/RECORD
