Metadata-Version: 2.1
Name: pyidaungsu
Version: 0.1.3
Summary: Python library for Pyidaungsu Myanmar languages
Home-page: https://github.com/kaunghtetsan275/pyidaungsu
Author: Kaung Htet San
Author-email: kaung@htetsan.me
License: UNKNOWN
Download-URL: https://github.com/kaunghtetsan275/pyidaungsu/archive/0.1.3.tar.gz
Platform: UNKNOWN
Classifier: Programming Language :: Python :: 3
Classifier: License :: OSI Approved :: MIT License
Classifier: Operating System :: OS Independent
Requires-Python: >=3.6
License-File: LICENSE
Requires-Dist: numpy
Requires-Dist: python-crfsuite
Requires-Dist: emoji
Requires-Dist: pybind11
Requires-Dist: fasttext
